askneedl_mcp_server/__init__.py
askneedl_mcp_server/__main__.py
askneedl_mcp_server/askneedl_fastmcp.py
askneedl_mcp_server/py.typed
askneedl_mcp_server-0.1.8.dist-info/METADATA
askneedl_mcp_server-0.1.8.dist-info/WHEEL
askneedl_mcp_server-0.1.8.dist-info/RECORD
