Metadata-Version: 2.4
Name: askneedl-mcp-server
Version: 0.1.8
Summary: MCP server for AskNeedl
Author-email: Needl AI Team <oneteam@needl.ai>
Requires-Python: >=3.11
Requires-Dist: fastmcp>=2.2.3
Requires-Dist: httpx>=0.28.1
Requires-Dist: pydantic>=2.11.3
